110-1/0502HW1/MUX.v

module MUX(
    input [3:0] in,
    input [1:0] s,
    output      z
);


//===================== Your Design Begin=====================
wire n1, n2, n3, n4,notS1,notS0;

not nS1(notS1,s[1]);
not nS0(notS0,s[0]);

and Q1(n1,in[0],notS1,notS0);
and Q2(n2,in[1],notS1,s[0]);
and Q3(n3,in[2],s[1],notS0);
and Q4(n4,in[3],s[1],s[0]);


or out(z,n1,n2,n3,n4);

//===================== Your Design End  =====================

endmodule

110-1/0502HW1/tb.v
`timescale 1ns/10ps
`define PAT "./pattern.dat"
`define EXP "./golden.dat"



module testfixture();
parameter N_EXP = 64;
parameter N_PAT = N_EXP;

reg [5:0] pat_mem [0:N_EXP-1];
reg exp_mem [0:N_EXP-1];



reg [1:0] S;
reg [3:0] in;
wire      z;

reg       exp_z;

integer i;
integer pass;
integer error;

MUX U1(
    .in(in),
    .s(S),
    .z(z)
);


initial begin
    $dumpfile("MUX.vcd");
    $dumpvars;

    $readmemb(`PAT, pat_mem);
    $readmemb(`EXP, exp_mem);

    pass  = 0; 
    error = 0;

    S = 0;
    in = 0;
    exp_z =0;
 
    $display("-----------------------------------------------------\n");
 	$display("START!!! Simulation Start .....\n");
 	$display("-----------------------------------------------------\n");
    #20; 

    for(i=0;i<N_EXP;i=i+1) begin
        {S, in} = pat_mem[i];
        exp_z   = exp_mem[i];

        #15;

        if( exp_z === z)
            pass = pass + 1; 
        else begin
            $display("FWPASS : Output %d are wrong! in=%b s=%b the real output is %b, but expected result is %b", i, in, S, z, exp_z);
            error = error + 1;
        end
    end
    

    $display("-------------------------------------------------------------\n");

    if(error == 0) begin
        $display("                       ALL PASS                            \n");
    end else begin
        $display("                  There are %d errors!                     \n", error);
    end

    $display("-------------------------------------------------------------\n");
    $finish;

end

endmodule

110-1/0502HW1/MUX.vcd
$date
	Mon May  9 15:34:04 2022
$end
$version
	Icarus Verilog
$end
$timescale
	10ps
$end
$scope module testfixture $end
$var wire 1 ! z $end
$var reg 2 " S [1:0] $end
$var reg 1 # exp_z $end
$var reg 4 $ in [3:0] $end
$var integer 32 % error [31:0] $end
$var integer 32 & i [31:0] $end
$var integer 32 ' pass [31:0] $end
$scope module U1 $end
$var wire 4 ( in [3:0] $end
$var wire 1 ) n1 $end
$var wire 1 * n2 $end
$var wire 1 + n3 $end
$var wire 1 , n4 $end
$var wire 1 - notS0 $end
$var wire 1 . notS1 $end
$var wire 2 / s [1:0] $end
$var wire 1 ! z $end
$upscope $end
$upscope $end
$enddefinitions $end
#0
$dumpvars
b0 /
1.
1-
0,
0+
0*
0)
b0 (
b0 '
bx &
b0 %
b0 $
0#
b0 "
0!
$end
#2000
b0 &
#3500
1!
1)
1#
b1 $
b1 (
b1 &
b1 '
#5000
0!
0)
0#
b10 $
b10 (
b10 &
b10 '
#6500
1!
1)
1#
b11 $
b11 (
b11 &
b11 '
#8000
0!
0)
0#
b100 $
b100 (
b100 &
b100 '
#9500
1!
1)
1#
b101 $
b101 (
b101 &
b101 '
#11000
0!
0)
0#
b110 $
b110 (
b110 &
b110 '
#12500
1!
1)
1#
b111 $
b111 (
b111 &
b111 '
#14000
0!
0)
0#
b1000 $
b1000 (
b1000 &
b1000 '
#15500
1!
1)
1#
b1001 $
b1001 (
b1001 &
b1001 '
#17000
0!
0)
0#
b1010 $
b1010 (
b1010 &
b1010 '
#18500
1!
1)
1#
b1011 $
b1011 (
b1011 &
b1011 '
#20000
0!
0)
0#
b1100 $
b1100 (
b1100 &
b1100 '
#21500
1!
1)
1#
b1101 $
b1101 (
b1101 &
b1101 '
#23000
0!
0)
0#
b1110 $
b1110 (
b1110 &
b1110 '
#24500
1!
1)
1#
b1111 $
b1111 (
b1111 &
b1111 '
#26000
0!
0-
0)
0#
b1 "
b1 /
b0 $
b0 (
b10000 &
b10000 '
#27500
b1 $
b1 (
b10001 &
b10001 '
#29000
1!
1*
1#
b10 $
b10 (
b10010 &
b10010 '
#30500
b11 $
b11 (
b10011 &
b10011 '
#32000
0!
0*
0#
b100 $
b100 (
b10100 &
b10100 '
#33500
b101 $
b101 (
b10101 &
b10101 '
#35000
1!
1*
1#
b110 $
b110 (
b10110 &
b10110 '
#36500
b111 $
b111 (
b10111 &
b10111 '
#38000
0!
0*
0#
b1000 $
b1000 (
b11000 &
b11000 '
#39500
b1001 $
b1001 (
b11001 &
b11001 '
#41000
1!
1*
1#
b1010 $
b1010 (
b11010 &
b11010 '
#42500
b1011 $
b1011 (
b11011 &
b11011 '
#44000
0!
0*
0#
b1100 $
b1100 (
b11100 &
b11100 '
#45500
b1101 $
b1101 (
b11101 &
b11101 '
#47000
1!
1*
1#
b1110 $
b1110 (
b11110 &
b11110 '
#48500
b1111 $
b1111 (
b11111 &
b11111 '
#50000
0!
0.
1-
0*
0#
b10 "
b10 /
b0 $
b0 (
b100000 &
b100000 '
#51500
b1 $
b1 (
b100001 &
b100001 '
#53000
b10 $
b10 (
b100010 &
b100010 '
#54500
b11 $
b11 (
b100011 &
b100011 '
#56000
1!
1+
1#
b100 $
b100 (
b100100 &
b100100 '
#57500
b101 $
b101 (
b100101 &
b100101 '
#59000
b110 $
b110 (
b100110 &
b100110 '
#60500
b111 $
b111 (
b100111 &
b100111 '
#62000
0!
0+
0#
b1000 $
b1000 (
b101000 &
b101000 '
#63500
b1001 $
b1001 (
b101001 &
b101001 '
#65000
b1010 $
b1010 (
b101010 &
b101010 '
#66500
b1011 $
b1011 (
b101011 &
b101011 '
#68000
1!
1+
1#
b1100 $
b1100 (
b101100 &
b101100 '
#69500
b1101 $
b1101 (
b101101 &
b101101 '
#71000
b1110 $
b1110 (
b101110 &
b101110 '
#72500
b1111 $
b1111 (
b101111 &
b101111 '
#74000
0!
0-
0+
0#
b11 "
b11 /
b0 $
b0 (
b110000 &
b110000 '
#75500
b1 $
b1 (
b110001 &
b110001 '
#77000
b10 $
b10 (
b110010 &
b110010 '
#78500
b11 $
b11 (
b110011 &
b110011 '
#80000
b100 $
b100 (
b110100 &
b110100 '
#81500
b101 $
b101 (
b110101 &
b110101 '
#83000
b110 $
b110 (
b110110 &
b110110 '
#84500
b111 $
b111 (
b110111 &
b110111 '
#86000
1!
1,
1#
b1000 $
b1000 (
b111000 &
b111000 '
#87500
b1001 $
b1001 (
b111001 &
b111001 '
#89000
b1010 $
b1010 (
b111010 &
b111010 '
#90500
b1011 $
b1011 (
b111011 &
b111011 '
#92000
b1100 $
b1100 (
b111100 &
b111100 '
#93500
b1101 $
b1101 (
b111101 &
b111101 '
#95000
b1110 $
b1110 (
b111110 &
b111110 '
#96500
b1111 $
b1111 (
b111111 &
b111111 '
#98000
b1000000 &
b1000000 '
